roc_auc_pairwise/sigmoid_pairwise_gpu.cpython-38-x86_64-linux-gnu.so
roc_auc_pairwise/utils.cpython-38-x86_64-linux-gnu.so
roc_auc_pairwise/sigmoid_pairwise_auc_gpu.cpython-38-x86_64-linux-gnu.so
roc_auc_pairwise/deltaauc_cpu.cpython-38-x86_64-linux-gnu.so
roc_auc_pairwise/sigmoid_pairwise_cpu.cpython-38-x86_64-linux-gnu.so
roc_auc_pairwise/deltaauc_gpu.cpython-38-x86_64-linux-gnu.so
roc_auc_pairwise/sigmoid_pairwise_auc_cpu.cpython-38-x86_64-linux-gnu.so
roc_auc_pairwise.libs/libcudart-e0aa9238.so.7.5.18
roc_auc_pairwise.libs/libgomp-e3b68c5f.so.1.0.0
roc_auc_pairwise-0.0.1.dist-info/METADATA
roc_auc_pairwise-0.0.1.dist-info/WHEEL
roc_auc_pairwise-0.0.1.dist-info/top_level.txt
roc_auc_pairwise-0.0.1.dist-info/LICENSE
roc_auc_pairwise-0.0.1.dist-info/RECORD
