Metadata-Version: 2.1
Name: roc_auc_pairwise
Version: 0.0.1
Author: Dmitry Michaylin
License-File: LICENSE
